{"ja_index.md":"783f1946","ja_installation_linux.md":"f5a8da80","ja_installation_windows.md":"468d632d","ja_troubleshooting_linux.md":"88aca314","ja_troubleshooting_windows.md":"3b8118ff","ja_usage_deepfloyd_if.md":"59c8db14","ja_usage_index.md":"db5f022d","en_troubleshooting_windows.md":"416ec365","en_usage_deepfloyd_if.md":"0d2bd501","ja_usage_model.md":"26749047","en_usage_model.md":"a7d9368c","en_usage_tensorrt.md":"2869f00c","index.md":"22c41307","ja_developers_documentation.md":"5c9b13a1","en_troubleshooting_linux.md":"fa5f3efb","en_developers_documentation.md":"5956f076","ja_developers_tensorrt.md":"5dfbef4c","en_index.md":"845c1223","en_installation_linux.md":"493e2b14","en_installation_windows.md":"58350a81","ja_usage_tensorrt.md":"e6e7f26a","en_developers_tensorrt.md":"435e1973","en_usage_index.md":"2e58ad3e"}
